cglue/__init__.py
cglue/cglue.py
cglue/cli.py
cglue/component.py
cglue/data_types.py
cglue/function.py
cglue/ports.py
cglue/signal.py
cglue/plugins/AsyncServerCalls.py
cglue/plugins/BuiltinDataTypes.py
cglue/plugins/Locks.py
cglue/plugins/ProjectConfigCompactor.py
cglue/plugins/RuntimeEvents.py
cglue/plugins/UserCodePlugin.py
cglue/plugins/__init__.py
cglue/runtime_generator/__init__.py
cglue/runtime_generator/context.py
cglue/utils/__init__.py
cglue/utils/common.py
cglue/utils/dict_processor.py
cglue/utils/filesystem.py
cglue/utils/multiple_instance_helpers.py
cglue/utils/version.py
CGlue-0.2.4.dist-info/LICENSE
CGlue-0.2.4.dist-info/METADATA
CGlue-0.2.4.dist-info/WHEEL
CGlue-0.2.4.dist-info/entry_points.txt
CGlue-0.2.4.dist-info/top_level.txt
CGlue-0.2.4.dist-info/RECORD
