Metadata-Version: 2.1
Name: CGlue
Version: 0.2.4
Summary: Framework for C software
Author-email: Dániel Buga <bugadani@gmail.com>
License: MIT License
Project-URL: Repository, https://github.com/RevolutionRobotics/CGlue
Requires-Python: >=3.7
License-File: LICENSE
